zwnet/__init__.py
zwnet/__version__.py
zwnet/http.py
zwnet/mprocessing.py
zwnet/mthreading.py
zwnet-0.0.1.dist-info/LICENSE
zwnet-0.0.1.dist-info/METADATA
zwnet-0.0.1.dist-info/WHEEL
zwnet-0.0.1.dist-info/top_level.txt
zwnet-0.0.1.dist-info/RECORD
